docsend2pdf_mcp/__init__.py
docsend2pdf_mcp/__main__.py
docsend2pdf_mcp/server.py
docsend2pdf_mcp-0.1.0.dist-info/METADATA
docsend2pdf_mcp-0.1.0.dist-info/WHEEL
docsend2pdf_mcp-0.1.0.dist-info/entry_points.txt
docsend2pdf_mcp-0.1.0.dist-info/licenses/LICENSE
docsend2pdf_mcp-0.1.0.dist-info/RECORD
