Metadata-Version: 2.4
Name: docsend2pdf-mcp
Version: 0.1.0
Summary: MCP server for converting DocSend documents to PDF via docsend2pdf.com
Author-email: Docsend2PDF <docsend2pdf@proton.me>
License-Expression: MIT
License-File: LICENSE
Requires-Python: >=3.8
Requires-Dist: aiofiles>=23.0.0
Requires-Dist: httpx>=0.25.0
Requires-Dist: mcp>=0.1.0
Provides-Extra: dev
Requires-Dist: black>=23.0.0; extra == 'dev'
Requires-Dist: mypy>=1.0.0; extra == 'dev'
Requires-Dist: pytest-asyncio>=0.21.0; extra == 'dev'
Requires-Dist: pytest>=7.0.0; extra == 'dev'
